py_writes_ts/__init__.py
py_writes_ts/class_to_interface.py
py_writes_ts/example_types.py
py_writes_ts/function_generator.py
py_writes_ts/import_generator.py
py_writes_ts/rename_interfaces.py
py_writes_ts/writer.py
py_writes_ts-1.0.1.dist-info/licenses/LICENSE.txt
py_writes_ts-1.0.1.dist-info/METADATA
py_writes_ts-1.0.1.dist-info/WHEEL
py_writes_ts-1.0.1.dist-info/top_level.txt
py_writes_ts-1.0.1.dist-info/RECORD
