Metadata-Version: 2.4
Name: py-writes-ts
Version: 1.0.1
Summary: Generate typescript code from python
Author-email: Oliver Sanz <oliverlsanz@gmail.com>
License:  The MIT License (MIT)
Project-URL: Homepage, https://github.com/OliverLSanz/py-writes-ts
Keywords: typescript
Classifier: Programming Language :: Python
Classifier: Programming Language :: Python :: 3
Requires-Python: >=3.12.8
License-File: LICENSE.txt
Provides-Extra: dev
Requires-Dist: pytest; extra == "dev"
Dynamic: license-file
